dash_rsuite_components/CheckTreePicker.py
dash_rsuite_components/__init__.py
dash_rsuite_components/_imports_.py
dash_rsuite_components/dash_rsuite_components.min.js
dash_rsuite_components/dash_rsuite_components.min.js.map
dash_rsuite_components/metadata.json
dash_rsuite_components/package-info.json
dash_rsuite_components-0.0.2.dist-info/LICENSE
dash_rsuite_components-0.0.2.dist-info/METADATA
dash_rsuite_components-0.0.2.dist-info/WHEEL
dash_rsuite_components-0.0.2.dist-info/top_level.txt
dash_rsuite_components-0.0.2.dist-info/RECORD
