Metadata-Version: 2.1
Name: dash_rsuite_components
Version: 0.0.2
Summary: Dash Rsuite Components is a Dash component library based on React Suite Components
Author: Martijn Doeleman <m.j.h.doeleman@umcutrecht.nl>
License: MIT
Classifier: Framework :: Dash
License-File: LICENSE
